gpt_automation/__init__.py
gpt_automation/main.py
gpt_automation/plugin_registry.json
gpt_automation/impl/__init__.py
gpt_automation/impl/base_plugin.py
gpt_automation/impl/directory_walker.py
gpt_automation/impl/logging_utils.py
gpt_automation/impl/plugin_impl/__init__.py
gpt_automation/impl/plugin_impl/plugin_class_loader.py
gpt_automation/impl/plugin_impl/plugin_context.py
gpt_automation/impl/plugin_impl/plugin_init.py
gpt_automation/impl/plugin_impl/plugin_interfaces.py
gpt_automation/impl/plugin_impl/plugin_loader.py
gpt_automation/impl/plugin_impl/plugin_settings.py
gpt_automation/impl/plugin_impl/plugin_utils.py
gpt_automation/impl/plugin_impl/utils/__init__.py
gpt_automation/impl/plugin_impl/utils/plugin_arg_filter.py
gpt_automation/impl/setting/__init__.py
gpt_automation/impl/setting/paths.py
gpt_automation/impl/setting/setting_models.py
gpt_automation/impl/setting/setting_utils.py
gpt_automation/impl/setting/settings_resolver.py
gpt_automation/impl/visitor/__init__.py
gpt_automation/impl/visitor/basevisitor.py
gpt_automation/plugins/__init__.py
gpt_automation/plugins/filter_plugin/__init__.py
gpt_automation/plugins/filter_plugin/manifest.json
gpt_automation/plugins/filter_plugin/paths.py
gpt_automation/plugins/filter_plugin/plugin.py
gpt_automation/plugins/filter_plugin/sample_config/black_list.txt
gpt_automation/plugins/filter_plugin/sample_config/white_list.txt
gpt_automation/plugins/ignore_plugin/Ignore_match.py
gpt_automation/plugins/ignore_plugin/__init__.py
gpt_automation/plugins/ignore_plugin/filters.py
gpt_automation/plugins/ignore_plugin/ignore_file_parser.py
gpt_automation/plugins/ignore_plugin/ignore_visitor.py
gpt_automation/plugins/ignore_plugin/manifest.json
gpt_automation/plugins/ignore_plugin/plugin.py
gpt_automation/plugins/ignore_plugin/third_party/__init__.py
gpt_automation/plugins/ignore_plugin/third_party/gitignore_parser2/__init__.py
gpt_automation/plugins/ignore_plugin/third_party/gitignore_parser2/parser.py
gpt_automation-0.1.17.dist-info/licenses/LICENSE
gpt_automation-0.1.17.dist-info/METADATA
gpt_automation-0.1.17.dist-info/WHEEL
gpt_automation-0.1.17.dist-info/entry_points.txt
gpt_automation-0.1.17.dist-info/top_level.txt
gpt_automation-0.1.17.dist-info/RECORD
