Metadata-Version: 2.4
Name: gpt_automation
Version: 0.1.17
Summary: GPT directory structure and file contents prompt generator
Author-email: Vinit <author@example.com>
License: 
Project-URL: Homepage, https://github.com/vrocky/gpt-automation/
Requires-Python: >=3.6
License-File: LICENSE
Requires-Dist: pyperclip==1.8.2
Requires-Dist: vrocky-gitignore-parser==0.1.12
Requires-Dist: chardet~=5.2.0
Dynamic: license-file
